xirr/__init__.py
xirr/math.py
xirr-0.1.8.dist-info/LICENSE.txt
xirr-0.1.8.dist-info/METADATA
xirr-0.1.8.dist-info/WHEEL
xirr-0.1.8.dist-info/top_level.txt
xirr-0.1.8.dist-info/RECORD
