Metadata-Version: 2.1
Name: xirr
Version: 0.1.8
Summary: xirr and xnpv calculators
Home-page: https://github.com/tarioch/xirr/
Author: Patrick Ruckstuhl
Author-email: patrick@ch.tario.org
License: MIT
Project-URL: Bug Tracker, https://github.com/tarioch/xirr/issues
Project-URL: Documentation, https://xirr.rtfd.io
Project-URL: Source Code, https://github.com/tarioch/xirr/
Platform: any
Classifier: Development Status :: 4 - Beta
Classifier: Programming Language :: Python
Classifier: Intended Audience :: Developers
Classifier: Topic :: Office/Business :: Financial
Classifier: Topic :: Office/Business :: Financial :: Accounting
Classifier: Topic :: Office/Business :: Financial :: Investment
Classifier: License :: OSI Approved :: MIT License
Provides-Extra: testing
License-File: LICENSE.txt
